[
  {
    "tag_name": "entity",
    "ids_to_tags": {
      "1": "B-codingAbility",
      "2": "I-codingAbility",
      "3": "L-codingAbility",
      "4": "U-codingAbility",
      "5": "B-studyField",
      "6": "I-studyField",
      "7": "L-studyField",
      "8": "U-studyField",
      "0": "O"
    },
    "tags_to_ids": {
      "B-codingAbility": 1,
      "I-codingAbility": 2,
      "L-codingAbility": 3,
      "U-codingAbility": 4,
      "B-studyField": 5,
      "I-studyField": 6,
      "L-studyField": 7,
      "U-studyField": 8,
      "O": 0
    },
    "num_tags": 9
  }
]